{
  "id": "input[type=reset]_element",
  "title": "input[type=\"reset\"] element",
  "type": "element",
  "description": "The input element represents a button that, when activated, resets the form.",
  "is_form_control": true,
  "references": [
    {
      "title": "WHATWG HTML spec for input[type=\"reset\"]",
      "url": "https://html.spec.whatwg.org/multipage/input.html#range-state-(type=range)"
    },
    {
      "title": "HTML AAM for the input[type=\"reset\"]",
      "url": "https://w3c.github.io/html-aam/#el-input-reset"
    }
  ],
  "assertions": [
    {
      "id": "convey_name",
      "examples": [
        "A screen reader might announce the button as something like \"<name>, button\".",
        "Voice control software will let the user say something like \"click <name>\" to activate the control."
      ],
      "css_target": "input[type=\"reset\"]"
    },
    {
      "id": "convey_role",
      "examples": [
        "A screen reader might be announce the role as something like \"button\".",
        "Voice control software will let the user say something like \"click button\" or flag the role with a number."
      ],
      "css_target": "input[type=\"reset\"]"
    },
    {
      "id": "provide_shortcuts",
      "css_target": "input[type=\"reset\"]"
    }
  ],
  "date_updated": "2021-09-14"
}
